{
    "success": true,
    "returnCode": "1001",
    "returnMessage": null,
    "data": {
        "total": 205222,
        "title": "wap图墙",
        "sort": "new",
        "isEnd": false,
        "cpc_offset": 0,
        "param": {
            "ptpWallDoc": "_wall_docs",
            "_mgjuuid": "e48d11a5-5a9c-412e-88df-920d3554964e",
            "sort": "new",
            "eventId": 70003,
            "cpc_offset": 0,
            "page": "2",
            "cKey": "wap-search",
            "cpcEventId": 70005,
            "ptpWallCpc": "_wall_cpc",
            "ptpPartC": "_mb_mls_0_wap-search_noab-noab",
            "section": "0",
            "minPrice": "5"
        },
        "page": 2,
        "list": [
            {
                "orgPrice": "￥220.80",
                "acm": "3.ms.2_4_1kajv04.0.8245-25176.94mObqhG3lx1q.t_0-lc_17",
                "iid": "1kajv04",
                "link": "http://item.meilishuo.com/h5/detail/1kajv04?acm=3.ms.2_4_1kajv04.0.8245-25176.94mObqhG3lx1q.t_0-lc_17",
                "clientUrl": "http://item.meilishuo.com/h5/detail/1kajv04?acm=3.ms.2_4_1kajv04.0.8245-25176.94mObqhG3lx1q.t_0-lc_17",
                "itemType": 1,
                "popularStar": null,
                "cparam": null,
                "itemMarks": "",
                "show": {
                    "w": 320,
                    "img": "http://s2.mogucdn.com/mlcdn/c45406/170419_68ceej7kldbgla01fc94l7e0130d2_640x960.jpg_320x999.jpg",
                    "h": 416
                },
                "type": 2,
                "sale": 1,
                "title": "七格格夏装新款韩版休闲无袖压皱荷叶边撞色绑带上衣女",
                "cfav": 8,
                "price": "￥110.40",
                "ptpC": "_mb_mls_0_wap-search_noab-noab",
                "lefttop_taglist": [
                    {
                        "img": "http://s18.mogucdn.com/b7/avatar/160520/1y0mpt_ie4tqodbgrrdcnlbhazdambqgqyde_50x54.jpg",
                        "w": 50,
                        "h": 54
                    }
                ],
                "showLarge": {
                    "img": "http://s2.mogucdn.com/mlcdn/c45406/170419_68ceej7kldbgla01fc94l7e0130d2_640x960.jpg_560x999.jpg",
                    "w": 560,
                    "h": 840
                },
                "leftbottom_taglist": []
            },
            {
                "orgPrice": "￥85.00",
                "acm": "3.ms.2_4_1kaj3mw.0.8245-25176.94mObqhG3lx1q.t_0-lc_17",
                "iid": "1kaj3mw",
                "link": "http://item.meilishuo.com/h5/detail/1kaj3mw?acm=3.ms.2_4_1kaj3mw.0.8245-25176.94mObqhG3lx1q.t_0-lc_17",
                "clientUrl": "http://item.meilishuo.com/h5/detail/1kaj3mw?acm=3.ms.2_4_1kaj3mw.0.8245-25176.94mObqhG3lx1q.t_0-lc_17",
                "itemType": 1,
                "popularStar": null,
                "cparam": null,
                "itemMarks": "",
                "show": {
                    "w": 320,
                    "img": "http://s2.mogucdn.com/mlcdn/c45406/170418_7ak9di1612k8l85fgj7kefe4g2l36_640x832.jpg_320x999.jpg",
                    "h": 416
                },
                "type": 2,
                "sale": 0,
                "title": "纯色圆领短袖袖口条纹T恤上衣青年韩版日系文艺打底衫复古汗衫潮",
                "cfav": 0,
                "price": "￥68.00",
                "ptpC": "_mb_mls_0_wap-search_noab-noab",
                "lefttop_taglist": [],
                "showLarge": {
                    "img": "http://s2.mogucdn.com/mlcdn/c45406/170418_7ak9di1612k8l85fgj7kefe4g2l36_640x832.jpg_560x999.jpg",
                    "w": 560,
                    "h": 728
                },
                "leftbottom_taglist": []
            },
            {
                "orgPrice": "￥85.00",
                "acm": "3.ms.2_4_1kaj3me.0.8245-25176.94mObqhG3lx1q.t_0-lc_17",
                "iid": "1kaj3me",
                "link": "http://item.meilishuo.com/h5/detail/1kaj3me?acm=3.ms.2_4_1kaj3me.0.8245-25176.94mObqhG3lx1q.t_0-lc_17",
                "clientUrl": "http://item.meilishuo.com/h5/detail/1kaj3me?acm=3.ms.2_4_1kaj3me.0.8245-25176.94mObqhG3lx1q.t_0-lc_17",
                "itemType": 1,
                "popularStar": null,
                "cparam": null,
                "itemMarks": "",
                "show": {
                    "w": 320,
                    "img": "http://s2.mogucdn.com/mlcdn/c45406/170418_72642efi671ll0494e7aj32g7ckfk_640x832.jpg_320x999.jpg",
                    "h": 416
                },
                "type": 2,
                "sale": 0,
                "title": "条纹卡通动漫印花短袖潮流时尚T恤上衣日系文艺男装复古打底衫潮",
                "cfav": 0,
                "price": "￥68.00",
                "ptpC": "_mb_mls_0_wap-search_noab-noab",
                "lefttop_taglist": [],
                "showLarge": {
                    "img": "http://s2.mogucdn.com/mlcdn/c45406/170418_72642efi671ll0494e7aj32g7ckfk_640x832.jpg_560x999.jpg",
                    "w": 560,
                    "h": 728
                },
                "leftbottom_taglist": []
            },
            {
                "orgPrice": "￥42.71",
                "acm": "3.ms.2_4_1kavecq.0.5806-25176.94mObqhG3lx1q.t_0-lc_17",
                "iid": "1kavecq",
                "link": "http://item.meilishuo.com/h5/detail/1kavecq?acm=3.ms.2_4_1kavecq.0.5806-25176.94mObqhG3lx1q.t_0-lc_17",
                "clientUrl": "http://item.meilishuo.com/h5/detail/1kavecq?acm=3.ms.2_4_1kavecq.0.5806-25176.94mObqhG3lx1q.t_0-lc_17",
                "itemType": 4,
                "popularStar": null,
                "cparam": null,
                "itemMarks": "",
                "show": {
                    "w": 320,
                    "img": "http://s2.mogucdn.com/mlcdn/c45406/170424_182a0be8lg5h7076226hc8fj04269_640x960.jpg_320x999.jpg",
                    "h": 416
                },
                "type": 2,
                "sale": 0,
                "title": "秋冬季韩版瑜伽服运动服健身服长袖t恤跑步上衣速干吸湿排汗修身",
                "cfav": 0,
                "price": "￥42.71",
                "ptpC": "_mb_mls_0_wap-search_noab-noab",
                "lefttop_taglist": [],
                "showLarge": {
                    "img": "http://s2.mogucdn.com/mlcdn/c45406/170424_182a0be8lg5h7076226hc8fj04269_640x960.jpg_560x999.jpg",
                    "w": 560,
                    "h": 840
                },
                "leftbottom_taglist": []
            },
            {
                "orgPrice": "￥58.00",
                "acm": "3.ms.2_1_1k9f6ok.1.5865-25176.94mObqhG3lx1q.t_0-lc_17-c_1_17_190940446_0_7_0-c1_",
                "iid": "1k9f6ok",
                "link": "http://item.meilishuo.com/h5/detail/1k9f6ok?acm=3.ms.2_1_1k9f6ok.1.5865-25176.94mObqhG3lx1q.t_0-lc_17-c_1_17_190940446_0_7_0-c1_&cparam=MTQ5MzAwMTc4N18xNmplZ2Q2XzNiNzQyODVjYjA0NGIzZWE2NDUwOTFhYTc3NzY2NDFhXzE3XzBfMTkwOTQwNDQ2XzAuNTc2Nl8wXzdfMV8zMTBfMF8w",
                "clientUrl": "http://item.meilishuo.com/h5/detail/1k9f6ok?acm=3.ms.2_1_1k9f6ok.1.5865-25176.94mObqhG3lx1q.t_0-lc_17-c_1_17_190940446_0_7_0-c1_&cparam=MTQ5MzAwMTc4N18xNmplZ2Q2XzNiNzQyODVjYjA0NGIzZWE2NDUwOTFhYTc3NzY2NDFhXzE3XzBfMTkwOTQwNDQ2XzAuNTc2Nl8wXzdfMV8zMTBfMF8w",
                "itemType": 3,
                "popularStar": null,
                "cparam": "MTQ5MzAwMTc4N18xNmplZ2Q2XzNiNzQyODVjYjA0NGIzZWE2NDUwOTFhYTc3NzY2NDFhXzE3XzBfMTkwOTQwNDQ2XzAuNTc2Nl8wXzdfMV8zMTBfMF8w",
                "itemMarks": "",
                "show": {
                    "w": 320,
                    "img": "http://s2.mogucdn.com/mlcdn/c45406/170401_38c4i0fck049j4fh38b3aabc5d1dc_640x832.png_320x999.jpg",
                    "h": 416
                },
                "type": 2,
                "sale": "323",
                "title": "2017春季新款女装韩版黑白条纹短袖T恤修身显瘦打底衫上衣",
                "cfav": "591",
                "price": "￥58.00",
                "ptpC": "_mb_mls_0_wap-search_noab-noab",
                "lefttop_taglist": [],
                "showLarge": {
                    "img": "http://s2.mogucdn.com/mlcdn/c45406/170401_38c4i0fck049j4fh38b3aabc5d1dc_640x832.png_560x999.jpg",
                    "w": 560,
                    "h": 728
                },
                "leftbottom_taglist": []
            },
            {
                "orgPrice": "￥58.00",
                "acm": "3.ms.2_1_1kab9va.1.5865-25176.94mObqhG3lx1q.t_0-lc_17-c_1_17_197692049_0_8_0-c1_",
                "iid": "1kab9va",
                "link": "http://item.meilishuo.com/h5/detail/1kab9va?acm=3.ms.2_1_1kab9va.1.5865-25176.94mObqhG3lx1q.t_0-lc_17-c_1_17_197692049_0_8_0-c1_&cparam=MTQ5MzAwMTc4N18xNmplZ2FpXzhjZWI0ZTI5MjFkZTI5ZWUxNGQ4YjllZjliNDZmMzFlXzE3XzFfMTk3NjkyMDQ5XzAuODQ2NF8wXzhfMV8yMThfMF8w",
                "clientUrl": "http://item.meilishuo.com/h5/detail/1kab9va?acm=3.ms.2_1_1kab9va.1.5865-25176.94mObqhG3lx1q.t_0-lc_17-c_1_17_197692049_0_8_0-c1_&cparam=MTQ5MzAwMTc4N18xNmplZ2FpXzhjZWI0ZTI5MjFkZTI5ZWUxNGQ4YjllZjliNDZmMzFlXzE3XzFfMTk3NjkyMDQ5XzAuODQ2NF8wXzhfMV8yMThfMF8w",
                "itemType": 3,
                "popularStar": null,
                "cparam": "MTQ5MzAwMTc4N18xNmplZ2FpXzhjZWI0ZTI5MjFkZTI5ZWUxNGQ4YjllZjliNDZmMzFlXzE3XzFfMTk3NjkyMDQ5XzAuODQ2NF8wXzhfMV8yMThfMF8w",
                "itemMarks": "",
                "show": {
                    "w": 320,
                    "img": "http://s2.mogucdn.com/mlcdn/55cf19/170415_6cajlclf460354j3dgfbea47ck489_640x960.jpg_320x999.jpg",
                    "h": 416
                },
                "type": 2,
                "sale": "73",
                "title": "2017春夏新款短袖亮片拼接T恤外穿宽松猫咪体恤上衣打底衫",
                "cfav": "10",
                "price": "￥58.00",
                "ptpC": "_mb_mls_0_wap-search_noab-noab",
                "lefttop_taglist": [],
                "showLarge": {
                    "img": "http://s2.mogucdn.com/mlcdn/55cf19/170415_6cajlclf460354j3dgfbea47ck489_640x960.jpg_560x999.jpg",
                    "w": 560,
                    "h": 840
                },
                "leftbottom_taglist": []
            },
            {
                "orgPrice": "￥36.00",
                "acm": "3.ms.2_4_1kave9q.0.5806-25176.94mObqhG3lx1q.t_0-lc_17",
                "iid": "1kave9q",
                "link": "http://item.meilishuo.com/h5/detail/1kave9q?acm=3.ms.2_4_1kave9q.0.5806-25176.94mObqhG3lx1q.t_0-lc_17",
                "clientUrl": "http://item.meilishuo.com/h5/detail/1kave9q?acm=3.ms.2_4_1kave9q.0.5806-25176.94mObqhG3lx1q.t_0-lc_17",
                "itemType": 4,
                "popularStar": null,
                "cparam": null,
                "itemMarks": "",
                "show": {
                    "w": 320,
                    "img": "http://s2.mogucdn.com/mlcdn/c45406/170424_374aaj7615l1ha4kf90a62hebiljd_640x960.jpg_320x999.jpg",
                    "h": 416
                },
                "type": 2,
                "sale": 0,
                "title": "【48元2件】秋季新款长袖t恤女圆领宽松学生体恤女印花打",
                "cfav": 0,
                "price": "￥36.00",
                "ptpC": "_mb_mls_0_wap-search_noab-noab",
                "lefttop_taglist": [],
                "showLarge": {
                    "img": "http://s2.mogucdn.com/mlcdn/c45406/170424_374aaj7615l1ha4kf90a62hebiljd_640x960.jpg_560x999.jpg",
                    "w": 560,
                    "h": 840
                },
                "leftbottom_taglist": []
            },
            {
                "orgPrice": "￥200.00",
                "acm": "3.ms.2_4_1kave8c.0.5806-25176.94mObqhG3lx1q.t_0-lc_17",
                "iid": "1kave8c",
                "link": "http://item.meilishuo.com/h5/detail/1kave8c?acm=3.ms.2_4_1kave8c.0.5806-25176.94mObqhG3lx1q.t_0-lc_17",
                "clientUrl": "http://item.meilishuo.com/h5/detail/1kave8c?acm=3.ms.2_4_1kave8c.0.5806-25176.94mObqhG3lx1q.t_0-lc_17",
                "itemType": 4,
                "popularStar": null,
                "cparam": null,
                "itemMarks": "",
                "show": {
                    "w": 320,
                    "img": "http://s2.mogucdn.com/mlcdn/c45406/170424_10j443bei7fi38ae1ebd9kl3ljdhk_640x960.jpg_320x999.jpg",
                    "h": 416
                },
                "type": 2,
                "sale": 0,
                "title": "夏季新款 韩版时尚套装女宽松短袖牛仔上衣阔腿短裤两件套装",
                "cfav": 0,
                "price": "￥200.00",
                "ptpC": "_mb_mls_0_wap-search_noab-noab",
                "lefttop_taglist": [],
                "showLarge": {
                    "img": "http://s2.mogucdn.com/mlcdn/c45406/170424_10j443bei7fi38ae1ebd9kl3ljdhk_640x960.jpg_560x999.jpg",
                    "w": 560,
                    "h": 840
                },
                "leftbottom_taglist": []
            },
            {
                "orgPrice": "￥99.00",
                "acm": "3.ms.2_4_1kave84.0.5806-25176.94mObqhG3lx1q.t_0-lc_17",
                "iid": "1kave84",
                "link": "http://item.meilishuo.com/h5/detail/1kave84?acm=3.ms.2_4_1kave84.0.5806-25176.94mObqhG3lx1q.t_0-lc_17",
                "clientUrl": "http://item.meilishuo.com/h5/detail/1kave84?acm=3.ms.2_4_1kave84.0.5806-25176.94mObqhG3lx1q.t_0-lc_17",
                "itemType": 4,
                "popularStar": null,
                "cparam": null,
                "itemMarks": "",
                "show": {
                    "w": 320,
                    "img": "http://s2.mogucdn.com/mlcdn/55cf19/170424_1133bd66j8jg6ff8e01hilkceefl0_640x960.jpg_320x999.jpg",
                    "h": 416
                },
                "type": 2,
                "sale": 0,
                "title": "2017孕妇套装无袖V领纯棉上衣+托腹短裤两件套",
                "cfav": 0,
                "price": "￥69.30",
                "ptpC": "_mb_mls_0_wap-search_noab-noab",
                "lefttop_taglist": [],
                "showLarge": {
                    "img": "http://s11.mogucdn.com/mlcdn/55cf19/170424_1133bd66j8jg6ff8e01hilkceefl0_640x960.jpg_560x999.jpg",
                    "w": 560,
                    "h": 840
                },
                "leftbottom_taglist": []
            },
            {
                "orgPrice": "￥98.00",
                "acm": "3.ms.2_4_1kave3i.0.5806-25176.94mObqhG3lx1q.t_0-lc_17",
                "iid": "1kave3i",
                "link": "http://item.meilishuo.com/h5/detail/1kave3i?acm=3.ms.2_4_1kave3i.0.5806-25176.94mObqhG3lx1q.t_0-lc_17",
                "clientUrl": "http://item.meilishuo.com/h5/detail/1kave3i?acm=3.ms.2_4_1kave3i.0.5806-25176.94mObqhG3lx1q.t_0-lc_17",
                "itemType": 4,
                "popularStar": null,
                "cparam": null,
                "itemMarks": "",
                "show": {
                    "w": 320,
                    "img": "http://s2.mogucdn.com/mlcdn/c45406/170424_1f7e5k6d8138i3becg920j8jh87lh_640x960.jpg_320x999.jpg",
                    "h": 416
                },
                "type": 2,
                "sale": 0,
                "title": "[唯依]宽松纯色V领荷叶袖雪纺衫+九分哈伦裤衣裤套装两件套",
                "cfav": 0,
                "price": "￥98.00",
                "ptpC": "_mb_mls_0_wap-search_noab-noab",
                "lefttop_taglist": [],
                "showLarge": {
                    "img": "http://s2.mogucdn.com/mlcdn/c45406/170424_1f7e5k6d8138i3becg920j8jh87lh_640x960.jpg_560x999.jpg",
                    "w": 560,
                    "h": 840
                },
                "leftbottom_taglist": []
            },
            {
                "orgPrice": "￥466.67",
                "acm": "3.ms.2_4_1kaizsu.0.8245-25176.94mObqhG3lx1q.t_0-lc_17",
                "iid": "1kaizsu",
                "link": "http://item.meilishuo.com/h5/detail/1kaizsu?acm=3.ms.2_4_1kaizsu.0.8245-25176.94mObqhG3lx1q.t_0-lc_17",
                "clientUrl": "http://item.meilishuo.com/h5/detail/1kaizsu?acm=3.ms.2_4_1kaizsu.0.8245-25176.94mObqhG3lx1q.t_0-lc_17",
                "itemType": 1,
                "popularStar": null,
                "cparam": null,
                "itemMarks": "",
                "show": {
                    "w": 320,
                    "img": "http://s2.mogucdn.com/mlcdn/c45406/170418_316bjb6flgedk9j9i56cbajebkl7a_933x1400.jpg_320x999.jpg",
                    "h": 416
                },
                "type": 2,
                "sale": 0,
                "title": "颖家原创设计师定制撞色印花透视衬衫宽松彩色上衣轻薄防晒衣女",
                "cfav": 1,
                "price": "￥168.00",
                "ptpC": "_mb_mls_0_wap-search_noab-noab",
                "lefttop_taglist": [
                    {
                        "img": "http://s18.mogucdn.com/b7/avatar/160520/1y0mpt_ie4tqodbgrrdcnlbhazdambqgqyde_50x54.jpg",
                        "w": 50,
                        "h": 54
                    }
                ],
                "showLarge": {
                    "img": "http://s2.mogucdn.com/mlcdn/c45406/170418_316bjb6flgedk9j9i56cbajebkl7a_933x1400.jpg_560x999.jpg",
                    "w": 560,
                    "h": 841
                },
                "leftbottom_taglist": []
            },
            {
                "orgPrice": "￥438.89",
                "acm": "3.ms.2_4_1kaixog.0.8245-25176.94mObqhG3lx1q.t_0-lc_17",
                "iid": "1kaixog",
                "link": "http://item.meilishuo.com/h5/detail/1kaixog?acm=3.ms.2_4_1kaixog.0.8245-25176.94mObqhG3lx1q.t_0-lc_17",
                "clientUrl": "http://item.meilishuo.com/h5/detail/1kaixog?acm=3.ms.2_4_1kaixog.0.8245-25176.94mObqhG3lx1q.t_0-lc_17",
                "itemType": 1,
                "popularStar": null,
                "cparam": null,
                "itemMarks": "",
                "show": {
                    "w": 320,
                    "img": "http://s2.mogucdn.com/mlcdn/c45406/170418_8d76l25ag1ee0g1fkdlgf9ijl4ia9_933x1400.jpg_320x999.jpg",
                    "h": 416
                },
                "type": 2,
                "sale": 0,
                "title": "颖家原创设计师定制黑白条纹可抽绳方领纯棉T恤宽松休闲女上衣",
                "cfav": 0,
                "price": "￥158.00",
                "ptpC": "_mb_mls_0_wap-search_noab-noab",
                "lefttop_taglist": [
                    {
                        "img": "http://s18.mogucdn.com/b7/avatar/160520/1y0mpt_ie4tqodbgrrdcnlbhazdambqgqyde_50x54.jpg",
                        "w": 50,
                        "h": 54
                    }
                ],
                "showLarge": {
                    "img": "http://s2.mogucdn.com/mlcdn/c45406/170418_8d76l25ag1ee0g1fkdlgf9ijl4ia9_933x1400.jpg_560x999.jpg",
                    "w": 560,
                    "h": 841
                },
                "leftbottom_taglist": []
            },
            {
                "orgPrice": "￥466.67",
                "acm": "3.ms.2_4_1kais8e.0.8245-25176.94mObqhG3lx1q.t_0-lc_17",
                "iid": "1kais8e",
                "link": "http://item.meilishuo.com/h5/detail/1kais8e?acm=3.ms.2_4_1kais8e.0.8245-25176.94mObqhG3lx1q.t_0-lc_17",
                "clientUrl": "http://item.meilishuo.com/h5/detail/1kais8e?acm=3.ms.2_4_1kais8e.0.8245-25176.94mObqhG3lx1q.t_0-lc_17",
                "itemType": 1,
                "popularStar": null,
                "cparam": null,
                "itemMarks": "",
                "show": {
                    "w": 320,
                    "img": "http://s2.mogucdn.com/mlcdn/c45406/170418_8dflc0bjl5674i78526hii82d9k44_933x1400.jpg_320x999.jpg",
                    "h": 416
                },
                "type": 2,
                "sale": 0,
                "title": "颖家原创设计师定制文艺灯笼袖系带纯棉衬衫减龄休闲上衣娃娃衫女",
                "cfav": 1,
                "price": "￥168.00",
                "ptpC": "_mb_mls_0_wap-search_noab-noab",
                "lefttop_taglist": [
                    {
                        "img": "http://s18.mogucdn.com/b7/avatar/160520/1y0mpt_ie4tqodbgrrdcnlbhazdambqgqyde_50x54.jpg",
                        "w": 50,
                        "h": 54
                    }
                ],
                "showLarge": {
                    "img": "http://s2.mogucdn.com/mlcdn/c45406/170418_8dflc0bjl5674i78526hii82d9k44_933x1400.jpg_560x999.jpg",
                    "w": 560,
                    "h": 841
                },
                "leftbottom_taglist": []
            },
            {
                "orgPrice": "￥42.71",
                "acm": "3.ms.2_4_1kave1s.0.5806-25176.94mObqhG3lx1q.t_0-lc_17",
                "iid": "1kave1s",
                "link": "http://item.meilishuo.com/h5/detail/1kave1s?acm=3.ms.2_4_1kave1s.0.5806-25176.94mObqhG3lx1q.t_0-lc_17",
                "clientUrl": "http://item.meilishuo.com/h5/detail/1kave1s?acm=3.ms.2_4_1kave1s.0.5806-25176.94mObqhG3lx1q.t_0-lc_17",
                "itemType": 4,
                "popularStar": null,
                "cparam": null,
                "itemMarks": "",
                "show": {
                    "w": 320,
                    "img": "http://s2.mogucdn.com/mlcdn/c45406/170424_7cblgf9l9ljbdj9addc444bacgh1a_720x1080.jpg_320x999.jpg",
                    "h": 416
                },
                "type": 2,
                "sale": 0,
                "title": "【菇凉家】秋季长袖T恤女韩版新款条纹拼接袖啤酒印花上衣体",
                "cfav": 0,
                "price": "￥42.71",
                "ptpC": "_mb_mls_0_wap-search_noab-noab",
                "lefttop_taglist": [],
                "showLarge": {
                    "img": "http://s2.mogucdn.com/mlcdn/c45406/170424_7cblgf9l9ljbdj9addc444bacgh1a_720x1080.jpg_560x999.jpg",
                    "w": 560,
                    "h": 840
                },
                "leftbottom_taglist": []
            },
            {
                "orgPrice": "￥55.00",
                "acm": "3.ms.2_1_1kabbn8.1.5865-25176.94mObqhG3lx1q.t_0-lc_17-c_1_17_197692001_0_9_0-c1_",
                "iid": "1kabbn8",
                "link": "http://item.meilishuo.com/h5/detail/1kabbn8?acm=3.ms.2_1_1kabbn8.1.5865-25176.94mObqhG3lx1q.t_0-lc_17-c_1_17_197692001_0_9_0-c1_&cparam=MTQ5MzAwMTc4N18xNmx3cW5lXzBmYzk2MTkxNmQxYzVkNWU5ODdlMTAwNWYwYmU1NjNjXzE3XzJfMTk3NjkyMDAxXzAuOTc1XzBfOV8xXzIxOF8wXzA=",
                "clientUrl": "http://item.meilishuo.com/h5/detail/1kabbn8?acm=3.ms.2_1_1kabbn8.1.5865-25176.94mObqhG3lx1q.t_0-lc_17-c_1_17_197692001_0_9_0-c1_&cparam=MTQ5MzAwMTc4N18xNmx3cW5lXzBmYzk2MTkxNmQxYzVkNWU5ODdlMTAwNWYwYmU1NjNjXzE3XzJfMTk3NjkyMDAxXzAuOTc1XzBfOV8xXzIxOF8wXzA=",
                "itemType": 3,
                "popularStar": null,
                "cparam": "MTQ5MzAwMTc4N18xNmx3cW5lXzBmYzk2MTkxNmQxYzVkNWU5ODdlMTAwNWYwYmU1NjNjXzE3XzJfMTk3NjkyMDAxXzAuOTc1XzBfOV8xXzIxOF8wXzA=",
                "itemMarks": "",
                "show": {
                    "w": 320,
                    "img": "http://s2.mogucdn.com/mlcdn/55cf19/170415_4j89f7e159e2jfg3glc834398d78d_640x960.jpg_320x999.jpg",
                    "h": 416
                },
                "type": 2,
                "sale": "60",
                "title": "冰淇淋t恤女短袖17夏季新款百搭打底衫学生印花纯棉宽松上衣",
                "cfav": "20",
                "price": "￥55.00",
                "ptpC": "_mb_mls_0_wap-search_noab-noab",
                "lefttop_taglist": [],
                "showLarge": {
                    "img": "http://s17.mogucdn.com/mlcdn/55cf19/170415_4j89f7e159e2jfg3glc834398d78d_640x960.jpg_560x999.jpg",
                    "w": 560,
                    "h": 840
                },
                "leftbottom_taglist": []
            },
            {
                "orgPrice": "￥85.00",
                "acm": "3.ms.2_1_1k99mp2.1.5865-25176.94mObqhG3lx1q.t_0-lc_17-c_1_17_199798233_0_10_0-c1_",
                "iid": "1k99mp2",
                "link": "http://item.meilishuo.com/h5/detail/1k99mp2?acm=3.ms.2_1_1k99mp2.1.5865-25176.94mObqhG3lx1q.t_0-lc_17-c_1_17_199798233_0_10_0-c1_&cparam=MTQ5MzAwMTc4N18xNmx3c3g2X2UwZDFmMmI4OWE0NjMzMWUyODAzNGNjNjExODAwZjI0XzE3XzNfMTk5Nzk4MjMzXzEuMF8wXzEwXzFfMTlfMF8w",
                "clientUrl": "http://item.meilishuo.com/h5/detail/1k99mp2?acm=3.ms.2_1_1k99mp2.1.5865-25176.94mObqhG3lx1q.t_0-lc_17-c_1_17_199798233_0_10_0-c1_&cparam=MTQ5MzAwMTc4N18xNmx3c3g2X2UwZDFmMmI4OWE0NjMzMWUyODAzNGNjNjExODAwZjI0XzE3XzNfMTk5Nzk4MjMzXzEuMF8wXzEwXzFfMTlfMF8w",
                "itemType": 3,
                "popularStar": null,
                "cparam": "MTQ5MzAwMTc4N18xNmx3c3g2X2UwZDFmMmI4OWE0NjMzMWUyODAzNGNjNjExODAwZjI0XzE3XzNfMTk5Nzk4MjMzXzEuMF8wXzEwXzFfMTlfMF8w",
                "itemMarks": "",
                "show": {
                    "w": 320,
                    "img": "http://s2.mogucdn.com/mlcdn/c45406/170330_2828jhkel4ljfg0f4a91il82el348_640x842.jpg_320x999.jpg",
                    "h": 416
                },
                "type": 2,
                "sale": "0",
                "title": "韩版小清新宽松显瘦卡通印花装饰体恤衫上衣学生纯棉短袖T恤女",
                "cfav": "0",
                "price": "￥59.50",
                "ptpC": "_mb_mls_0_wap-search_noab-noab",
                "lefttop_taglist": [],
                "showLarge": {
                    "img": "http://s2.mogucdn.com/mlcdn/c45406/170330_2828jhkel4ljfg0f4a91il82el348_640x842.jpg_560x999.jpg",
                    "w": 560,
                    "h": 737
                },
                "leftbottom_taglist": []
            },
            {
                "orgPrice": "￥99.00",
                "acm": "3.ms.2_4_1kave1c.0.5806-25176.94mObqhG3lx1q.t_0-lc_17",
                "iid": "1kave1c",
                "link": "http://item.meilishuo.com/h5/detail/1kave1c?acm=3.ms.2_4_1kave1c.0.5806-25176.94mObqhG3lx1q.t_0-lc_17",
                "clientUrl": "http://item.meilishuo.com/h5/detail/1kave1c?acm=3.ms.2_4_1kave1c.0.5806-25176.94mObqhG3lx1q.t_0-lc_17",
                "itemType": 4,
                "popularStar": null,
                "cparam": null,
                "itemMarks": "",
                "show": {
                    "w": 320,
                    "img": "http://s2.mogucdn.com/mlcdn/55cf19/170424_1daee8jghkac3eclb387fk75li46e_640x960.jpg_320x999.jpg",
                    "h": 416
                },
                "type": 2,
                "sale": 0,
                "title": "2017夏装新款孕妇装上衣字母印花图案＋托腹裤两件套装",
                "cfav": 0,
                "price": "￥69.30",
                "ptpC": "_mb_mls_0_wap-search_noab-noab",
                "lefttop_taglist": [],
                "showLarge": {
                    "img": "http://s2.mogucdn.com/mlcdn/55cf19/170424_1daee8jghkac3eclb387fk75li46e_640x960.jpg_560x999.jpg",
                    "w": 560,
                    "h": 840
                },
                "leftbottom_taglist": []
            },
            {
                "orgPrice": "￥59.70",
                "acm": "3.ms.2_4_1kavdz2.0.5806-25176.94mObqhG3lx1q.t_0-lc_17",
                "iid": "1kavdz2",
                "link": "http://item.meilishuo.com/h5/detail/1kavdz2?acm=3.ms.2_4_1kavdz2.0.5806-25176.94mObqhG3lx1q.t_0-lc_17",
                "clientUrl": "http://item.meilishuo.com/h5/detail/1kavdz2?acm=3.ms.2_4_1kavdz2.0.5806-25176.94mObqhG3lx1q.t_0-lc_17",
                "itemType": 4,
                "popularStar": null,
                "cparam": null,
                "itemMarks": "",
                "show": {
                    "w": 320,
                    "img": "http://s2.mogucdn.com/mlcdn/c45406/170424_18h0ll7cg35bi5b5hgdj8iaab2llf_640x842.jpg_320x999.jpg",
                    "h": 416
                },
                "type": 2,
                "sale": 0,
                "title": "夏季新款时尚字母印花短袖T恤女宽松百搭网纱拼接透视打底上衣潮",
                "cfav": 0,
                "price": "￥59.70",
                "ptpC": "_mb_mls_0_wap-search_noab-noab",
                "lefttop_taglist": [],
                "showLarge": {
                    "img": "http://s2.mogucdn.com/mlcdn/c45406/170424_18h0ll7cg35bi5b5hgdj8iaab2llf_640x842.jpg_560x999.jpg",
                    "w": 560,
                    "h": 737
                },
                "leftbottom_taglist": []
            },
            {
                "orgPrice": "￥45.00",
                "acm": "3.ms.2_4_1kavdue.0.5806-25176.94mObqhG3lx1q.t_0-lc_17",
                "iid": "1kavdue",
                "link": "http://item.meilishuo.com/h5/detail/1kavdue?acm=3.ms.2_4_1kavdue.0.5806-25176.94mObqhG3lx1q.t_0-lc_17",
                "clientUrl": "http://item.meilishuo.com/h5/detail/1kavdue?acm=3.ms.2_4_1kavdue.0.5806-25176.94mObqhG3lx1q.t_0-lc_17",
                "itemType": 4,
                "popularStar": null,
                "cparam": null,
                "itemMarks": "",
                "show": {
                    "w": 320,
                    "img": "http://s2.mogucdn.com/mlcdn/c45406/170424_1jik0jed2h7773gi3f756967l3iid_640x842.jpg_320x999.jpg",
                    "h": 416
                },
                "type": 2,
                "sale": 0,
                "title": "棉夏季男士短袖T恤男装潮圆领纯色体恤打底衫韩版半袖上衣夏装",
                "cfav": 0,
                "price": "￥45.00",
                "ptpC": "_mb_mls_0_wap-search_noab-noab",
                "lefttop_taglist": [],
                "showLarge": {
                    "img": "http://s2.mogucdn.com/mlcdn/c45406/170424_1jik0jed2h7773gi3f756967l3iid_640x842.jpg_560x999.jpg",
                    "w": 560,
                    "h": 737
                },
                "leftbottom_taglist": []
            },
            {
                "orgPrice": "￥84.29",
                "acm": "3.ms.2_4_1kavdtk.0.5806-25176.94mObqhG3lx1q.t_0-lc_17",
                "iid": "1kavdtk",
                "link": "http://item.meilishuo.com/h5/detail/1kavdtk?acm=3.ms.2_4_1kavdtk.0.5806-25176.94mObqhG3lx1q.t_0-lc_17",
                "clientUrl": "http://item.meilishuo.com/h5/detail/1kavdtk?acm=3.ms.2_4_1kavdtk.0.5806-25176.94mObqhG3lx1q.t_0-lc_17",
                "itemType": 4,
                "popularStar": null,
                "cparam": null,
                "itemMarks": "",
                "show": {
                    "w": 320,
                    "img": "http://s2.mogucdn.com/mlcdn/c45406/170424_6745gc66e2019lh36952l71i116h1_640x960.jpg_320x999.jpg",
                    "h": 416
                },
                "type": 2,
                "sale": 0,
                "title": "性感一字领露肩吊带雪纺衫女短款宽松亮丝打底衫上衣",
                "cfav": 0,
                "price": "￥59.00",
                "ptpC": "_mb_mls_0_wap-search_noab-noab",
                "lefttop_taglist": [],
                "showLarge": {
                    "img": "http://s2.mogucdn.com/mlcdn/c45406/170424_6745gc66e2019lh36952l71i116h1_640x960.jpg_560x999.jpg",
                    "w": 560,
                    "h": 840
                },
                "leftbottom_taglist": []
            },
            {
                "orgPrice": "￥466.67",
                "acm": "3.ms.2_4_1kairou.0.8245-25176.94mObqhG3lx1q.t_0-lc_17",
                "iid": "1kairou",
                "link": "http://item.meilishuo.com/h5/detail/1kairou?acm=3.ms.2_4_1kairou.0.8245-25176.94mObqhG3lx1q.t_0-lc_17",
                "clientUrl": "http://item.meilishuo.com/h5/detail/1kairou?acm=3.ms.2_4_1kairou.0.8245-25176.94mObqhG3lx1q.t_0-lc_17",
                "itemType": 1,
                "popularStar": null,
                "cparam": null,
                "itemMarks": "",
                "show": {
                    "w": 320,
                    "img": "http://s2.mogucdn.com/mlcdn/c45406/170418_4g1151l06i743jek88i1h99534k36_800x1200.jpg_320x999.jpg",
                    "h": 416
                },
                "type": 2,
                "sale": 0,
                "title": "颖家原创设计潮牌热带印花真丝感轻薄翻领衬衫宽松透视上衣女衬衣",
                "cfav": 0,
                "price": "￥168.00",
                "ptpC": "_mb_mls_0_wap-search_noab-noab",
                "lefttop_taglist": [
                    {
                        "img": "http://s18.mogucdn.com/b7/avatar/160520/1y0mpt_ie4tqodbgrrdcnlbhazdambqgqyde_50x54.jpg",
                        "w": 50,
                        "h": 54
                    }
                ],
                "showLarge": {
                    "img": "http://s2.mogucdn.com/mlcdn/c45406/170418_4g1151l06i743jek88i1h99534k36_800x1200.jpg_560x999.jpg",
                    "w": 560,
                    "h": 840
                },
                "leftbottom_taglist": []
            },
            {
                "orgPrice": "￥248.00",
                "acm": "3.ms.2_4_1kahf5a.0.8245-25176.94mObqhG3lx1q.t_0-lc_17",
                "iid": "1kahf5a",
                "link": "http://item.meilishuo.com/h5/detail/1kahf5a?acm=3.ms.2_4_1kahf5a.0.8245-25176.94mObqhG3lx1q.t_0-lc_17",
                "clientUrl": "http://item.meilishuo.com/h5/detail/1kahf5a?acm=3.ms.2_4_1kahf5a.0.8245-25176.94mObqhG3lx1q.t_0-lc_17",
                "itemType": 1,
                "popularStar": null,
                "cparam": null,
                "itemMarks": "",
                "show": {
                    "w": 320,
                    "img": "http://s2.mogucdn.com/mlcdn/c45406/170418_7a99e32cj620cfc62ih2l6d9ae540_640x960.jpg_320x999.jpg",
                    "h": 416
                },
                "type": 2,
                "sale": 2,
                "title": "1313 宽松短袖t恤式OP英文刺绣腰带简约连衣裙15762",
                "cfav": 12,
                "price": "￥124.00",
                "ptpC": "_mb_mls_0_wap-search_noab-noab",
                "lefttop_taglist": [
                    {
                        "img": "http://s18.mogucdn.com/b7/avatar/160520/1y0mpt_ie4tqodbgrrdcnlbhazdambqgqyde_50x54.jpg",
                        "w": 50,
                        "h": 54
                    }
                ],
                "showLarge": {
                    "img": "http://s2.mogucdn.com/mlcdn/c45406/170418_7a99e32cj620cfc62ih2l6d9ae540_640x960.jpg_560x999.jpg",
                    "w": 560,
                    "h": 840
                },
                "leftbottom_taglist": []
            },
            {
                "orgPrice": "￥498.00",
                "acm": "3.ms.2_4_1kaheuw.0.8245-25176.94mObqhG3lx1q.t_0-lc_17",
                "iid": "1kaheuw",
                "link": "http://item.meilishuo.com/h5/detail/1kaheuw?acm=3.ms.2_4_1kaheuw.0.8245-25176.94mObqhG3lx1q.t_0-lc_17",
                "clientUrl": "http://item.meilishuo.com/h5/detail/1kaheuw?acm=3.ms.2_4_1kaheuw.0.8245-25176.94mObqhG3lx1q.t_0-lc_17",
                "itemType": 1,
                "popularStar": null,
                "cparam": null,
                "itemMarks": "",
                "show": {
                    "w": 320,
                    "img": "http://s2.mogucdn.com/mlcdn/c45406/170418_15608ifh90hhe5bc378e7gbhbch81_640x960.jpg_320x999.jpg",
                    "h": 416
                },
                "type": 2,
                "sale": 0,
                "title": "1313 条纹衬衫开叉长袖多穿设计翻领衬衣女中长款15759",
                "cfav": 2,
                "price": "￥249.00",
                "ptpC": "_mb_mls_0_wap-search_noab-noab",
                "lefttop_taglist": [
                    {
                        "img": "http://s18.mogucdn.com/b7/avatar/160520/1y0mpt_ie4tqodbgrrdcnlbhazdambqgqyde_50x54.jpg",
                        "w": 50,
                        "h": 54
                    }
                ],
                "showLarge": {
                    "img": "http://s2.mogucdn.com/mlcdn/c45406/170418_15608ifh90hhe5bc378e7gbhbch81_640x960.jpg_560x999.jpg",
                    "w": 560,
                    "h": 840
                },
                "leftbottom_taglist": []
            },
            {
                "orgPrice": "￥42.00",
                "acm": "3.ms.2_4_1kavdso.0.5806-25176.94mObqhG3lx1q.t_0-lc_17",
                "iid": "1kavdso",
                "link": "http://item.meilishuo.com/h5/detail/1kavdso?acm=3.ms.2_4_1kavdso.0.5806-25176.94mObqhG3lx1q.t_0-lc_17",
                "clientUrl": "http://item.meilishuo.com/h5/detail/1kavdso?acm=3.ms.2_4_1kavdso.0.5806-25176.94mObqhG3lx1q.t_0-lc_17",
                "itemType": 4,
                "popularStar": null,
                "cparam": null,
                "itemMarks": "",
                "show": {
                    "w": 320,
                    "img": "http://s2.mogucdn.com/mlcdn/c45406/170424_7jiikd1d18751gadac4f3ik63ad45_640x960.png_320x999.jpg",
                    "h": 416
                },
                "type": 2,
                "sale": 0,
                "title": "春夏女装韩版学院风荷叶边娃娃衫无袖短款背心学生外穿上衣打底衫",
                "cfav": 0,
                "price": "￥42.00",
                "ptpC": "_mb_mls_0_wap-search_noab-noab",
                "lefttop_taglist": [],
                "showLarge": {
                    "img": "http://s2.mogucdn.com/mlcdn/c45406/170424_7jiikd1d18751gadac4f3ik63ad45_640x960.png_560x999.jpg",
                    "w": 560,
                    "h": 840
                },
                "leftbottom_taglist": []
            },
            {
                "orgPrice": "￥85.00",
                "acm": "3.ms.2_1_1ka58u8.1.5865-25176.94mObqhG3lx1q.t_0-lc_17-c_1_17_199799705_0_11_0-c1_",
                "iid": "1ka58u8",
                "link": "http://item.meilishuo.com/h5/detail/1ka58u8?acm=3.ms.2_1_1ka58u8.1.5865-25176.94mObqhG3lx1q.t_0-lc_17-c_1_17_199799705_0_11_0-c1_&cparam=MTQ5MzAwMTc4N18xNmx3dnh1X2EyM2Y4NWJjYzMwZmIyYjYxZDQ4N2JjNDlkMjNhNDlhXzE3XzRfMTk5Nzk5NzA1XzEuMF8wXzExXzFfMTlfMF8w",
                "clientUrl": "http://item.meilishuo.com/h5/detail/1ka58u8?acm=3.ms.2_1_1ka58u8.1.5865-25176.94mObqhG3lx1q.t_0-lc_17-c_1_17_199799705_0_11_0-c1_&cparam=MTQ5MzAwMTc4N18xNmx3dnh1X2EyM2Y4NWJjYzMwZmIyYjYxZDQ4N2JjNDlkMjNhNDlhXzE3XzRfMTk5Nzk5NzA1XzEuMF8wXzExXzFfMTlfMF8w",
                "itemType": 3,
                "popularStar": null,
                "cparam": "MTQ5MzAwMTc4N18xNmx3dnh1X2EyM2Y4NWJjYzMwZmIyYjYxZDQ4N2JjNDlkMjNhNDlhXzE3XzRfMTk5Nzk5NzA1XzEuMF8wXzExXzFfMTlfMF8w",
                "itemMarks": "",
                "show": {
                    "w": 320,
                    "img": "http://s2.mogucdn.com/mlcdn/c45406/170412_0kdc3hfij1ejgbc632f0lc0j1a743_640x842.jpg_320x999.jpg",
                    "h": 416
                },
                "type": 2,
                "sale": "0",
                "title": "夏季新品韩版宽松亮片贴布五角星短袖T恤女学生打底衫上衣体恤潮",
                "cfav": "0",
                "price": "￥59.50",
                "ptpC": "_mb_mls_0_wap-search_noab-noab",
                "lefttop_taglist": [],
                "showLarge": {
                    "img": "http://s2.mogucdn.com/mlcdn/c45406/170412_0kdc3hfij1ejgbc632f0lc0j1a743_640x842.jpg_560x999.jpg",
                    "w": 560,
                    "h": 737
                },
                "leftbottom_taglist": []
            },
            {
                "orgPrice": "￥85.00",
                "acm": "3.ms.2_1_1k9tc2g.1.5865-25176.94mObqhG3lx1q.t_0-lc_17-c_1_17_199801661_0_12_0-c1_",
                "iid": "1k9tc2g",
                "link": "http://item.meilishuo.com/h5/detail/1k9tc2g?acm=3.ms.2_1_1k9tc2g.1.5865-25176.94mObqhG3lx1q.t_0-lc_17-c_1_17_199801661_0_12_0-c1_&cparam=MTQ5MzAwMTc4N18xMWtfM2JkYmQ0ZDZmMGJmZGJjMTAyMTM3Yzc3MjBhYjdiMjFfMTdfNV8xOTk4MDE2NjFfMF8wXzEyXzFfMTlfMF8w",
                "clientUrl": "http://item.meilishuo.com/h5/detail/1k9tc2g?acm=3.ms.2_1_1k9tc2g.1.5865-25176.94mObqhG3lx1q.t_0-lc_17-c_1_17_199801661_0_12_0-c1_&cparam=MTQ5MzAwMTc4N18xMWtfM2JkYmQ0ZDZmMGJmZGJjMTAyMTM3Yzc3MjBhYjdiMjFfMTdfNV8xOTk4MDE2NjFfMF8wXzEyXzFfMTlfMF8w",
                "itemType": 3,
                "popularStar": null,
                "cparam": "MTQ5MzAwMTc4N18xMWtfM2JkYmQ0ZDZmMGJmZGJjMTAyMTM3Yzc3MjBhYjdiMjFfMTdfNV8xOTk4MDE2NjFfMF8wXzEyXzFfMTlfMF8w",
                "itemMarks": "",
                "show": {
                    "w": 320,
                    "img": "http://s2.mogucdn.com/mlcdn/c45406/170408_2kjf35b53cg05734937b2bd6he47c_640x842.jpg_320x999.jpg",
                    "h": 416
                },
                "type": 2,
                "sale": "0",
                "title": "夏季新款韩版女装宽松显瘦洗水破洞短袖上衣学生短款迷彩T恤女潮",
                "cfav": "1",
                "price": "￥59.50",
                "ptpC": "_mb_mls_0_wap-search_noab-noab",
                "lefttop_taglist": [],
                "showLarge": {
                    "img": "http://s2.mogucdn.com/mlcdn/c45406/170408_2kjf35b53cg05734937b2bd6he47c_640x842.jpg_560x999.jpg",
                    "w": 560,
                    "h": 737
                },
                "leftbottom_taglist": []
            },
            {
                "orgPrice": "￥81.29",
                "acm": "3.ms.2_4_1kavdqc.0.5806-25176.94mObqhG3lx1q.t_0-lc_17",
                "iid": "1kavdqc",
                "link": "http://item.meilishuo.com/h5/detail/1kavdqc?acm=3.ms.2_4_1kavdqc.0.5806-25176.94mObqhG3lx1q.t_0-lc_17",
                "clientUrl": "http://item.meilishuo.com/h5/detail/1kavdqc?acm=3.ms.2_4_1kavdqc.0.5806-25176.94mObqhG3lx1q.t_0-lc_17",
                "itemType": 4,
                "popularStar": null,
                "cparam": null,
                "itemMarks": "61",
                "show": {
                    "w": 320,
                    "img": "http://s2.mogucdn.com/p2/uni/170423/3elv73_257h42b6eeclkifk40lc61he27e6d_640x960.jpg_320x999.jpg",
                    "h": 416
                },
                "type": 2,
                "sale": 0,
                "title": "韩版夏季新款反印字母短袖T恤宽松打底体恤",
                "cfav": 0,
                "price": "￥81.29",
                "ptpC": "_mb_mls_0_wap-search_noab-noab",
                "lefttop_taglist": [],
                "showLarge": {
                    "img": "http://s2.mogucdn.com/p2/uni/170423/3elv73_257h42b6eeclkifk40lc61he27e6d_640x960.jpg_560x999.jpg",
                    "w": 560,
                    "h": 840
                },
                "leftbottom_taglist": []
            },
            {
                "orgPrice": "￥49.98",
                "acm": "3.ms.2_4_1kavdpy.0.5806-25176.94mObqhG3lx1q.t_0-lc_17",
                "iid": "1kavdpy",
                "link": "http://item.meilishuo.com/h5/detail/1kavdpy?acm=3.ms.2_4_1kavdpy.0.5806-25176.94mObqhG3lx1q.t_0-lc_17",
                "clientUrl": "http://item.meilishuo.com/h5/detail/1kavdpy?acm=3.ms.2_4_1kavdpy.0.5806-25176.94mObqhG3lx1q.t_0-lc_17",
                "itemType": 4,
                "popularStar": null,
                "cparam": null,
                "itemMarks": "",
                "show": {
                    "w": 320,
                    "img": "http://s2.mogucdn.com/mlcdn/c45406/170424_6614g562i1h2d81c6h4ka360bjl2k_640x842.jpg_320x999.jpg",
                    "h": 416
                },
                "type": 2,
                "sale": 0,
                "title": "春夏女装韩版少女中长款开叉短袖学生T桖上衣",
                "cfav": 0,
                "price": "￥49.98",
                "ptpC": "_mb_mls_0_wap-search_noab-noab",
                "lefttop_taglist": [],
                "showLarge": {
                    "img": "http://s2.mogucdn.com/mlcdn/c45406/170424_6614g562i1h2d81c6h4ka360bjl2k_640x842.jpg_560x999.jpg",
                    "w": 560,
                    "h": 737
                },
                "leftbottom_taglist": []
            },
            {
                "orgPrice": "￥98.00",
                "acm": "3.ms.2_4_1kavdo2.0.5806-25176.94mObqhG3lx1q.t_0-lc_17",
                "iid": "1kavdo2",
                "link": "http://item.meilishuo.com/h5/detail/1kavdo2?acm=3.ms.2_4_1kavdo2.0.5806-25176.94mObqhG3lx1q.t_0-lc_17",
                "clientUrl": "http://item.meilishuo.com/h5/detail/1kavdo2?acm=3.ms.2_4_1kavdo2.0.5806-25176.94mObqhG3lx1q.t_0-lc_17",
                "itemType": 4,
                "popularStar": null,
                "cparam": null,
                "itemMarks": "",
                "show": {
                    "w": 320,
                    "img": "http://s2.mogucdn.com/mlcdn/c45406/170424_8gf1h7gbid08ijfk7fk8kd0179cf4_640x960.jpg_320x999.jpg",
                    "h": 416
                },
                "type": 2,
                "sale": 0,
                "title": "[唯依]新款无袖露脐上衣+九分蕾丝阔腿裤套装两件套",
                "cfav": 0,
                "price": "￥98.00",
                "ptpC": "_mb_mls_0_wap-search_noab-noab",
                "lefttop_taglist": [],
                "showLarge": {
                    "img": "http://s2.mogucdn.com/mlcdn/c45406/170424_8gf1h7gbid08ijfk7fk8kd0179cf4_640x960.jpg_560x999.jpg",
                    "w": 560,
                    "h": 840
                },
                "leftbottom_taglist": []
            },
            {
                "orgPrice": "￥90.00",
                "acm": "3.ms.2_4_1kavdky.0.5806-25176.94mObqhG3lx1q.t_0-lc_17",
                "iid": "1kavdky",
                "link": "http://item.meilishuo.com/h5/detail/1kavdky?acm=3.ms.2_4_1kavdky.0.5806-25176.94mObqhG3lx1q.t_0-lc_17",
                "clientUrl": "http://item.meilishuo.com/h5/detail/1kavdky?acm=3.ms.2_4_1kavdky.0.5806-25176.94mObqhG3lx1q.t_0-lc_17",
                "itemType": 4,
                "popularStar": null,
                "cparam": null,
                "itemMarks": "",
                "show": {
                    "w": 320,
                    "img": "http://s2.mogucdn.com/mlcdn/c45406/170424_36h3a888bf72h91896f72bcb66alj_640x842.jpg_320x999.jpg",
                    "h": 416
                },
                "type": 2,
                "sale": 0,
                "title": "2017夏季新款女装韩版百搭条纹短袖t恤女宽松学生半袖上衣体",
                "cfav": 0,
                "price": "￥63.00",
                "ptpC": "_mb_mls_0_wap-search_noab-noab",
                "lefttop_taglist": [],
                "showLarge": {
                    "img": "http://s2.mogucdn.com/mlcdn/c45406/170424_36h3a888bf72h91896f72bcb66alj_640x842.jpg_560x999.jpg",
                    "w": 560,
                    "h": 737
                },
                "leftbottom_taglist": []
            }
        ],
        "ptpPartC": "_mb_mls_0_wap-search_noab-noab",
        "filter": {
            "title": "wap图墙",
            "list": [
                {
                    "title": "综合",
                    "sort": "pop",
                    "style": null,
                    "fcid": "null",
                    "type": "sort"
                },
                {
                    "title": "销量",
                    "sort": "sell",
                    "style": null,
                    "fcid": "null",
                    "type": "sort"
                },
                {
                    "title": "最新",
                    "sort": "new",
                    "style": null,
                    "fcid": "null",
                    "type": "sort"
                }
            ]
        }
    }
}