{
    "data": {
        "context": {
            "currentTime": 1493033663
        },
        "isEnd": false,
        "list": [
            {
                "tagLink1": "mls://search/result?keyword=V领上衣",
                "tagLink2": "",
                "tagLink3": "",
                "acm": "3.mce.2_10_1b9ji.9439.0.zlmCBqhId66VR.m_262763",
                "link": "http://item.meilishuo.com/h5/detail/1gp63p6?mt=12.9439.r189899.11228&acm=3.mce.2_10_1b9ji.9439.0.zlmCBqhId66VR.m_262763",
                "image": "http://s8.mogucdn.com/p2/161013/1sd_43444fb0a20l6elk6d2jd7f6dg435_750x772.jpg",
                "popularStar": "5",
                "endTime": 0,
                "startTime": 1477030942,
                "title": "V领上衣",
                "tag2": "",
                "tag3": "",
                "description": "今年火到不行的复古风上衣，别致V领，柔软绒雪纺，出彩搭配，你不来一件？",
                "tag1": "V领上衣"
            },
            {
                "tagLink1": "mls://search/result?keyword=套装",
                "tagLink2": "",
                "tagLink3": "",
                "acm": "3.mce.2_10_1b9jk.9439.0.zlmCBqhId66VS.m_262764",
                "link": "http://item.meilishuo.com/h5/detail/1gmvcuy?mt=12.9439.r189890.11228&acm=3.mce.2_10_1b9jk.9439.0.zlmCBqhId66VS.m_262764",
                "image": "http://s10.mogucdn.com/p2/161013/1sd_2bb6h8i2bc62lll9glcbf0gb35ie8_400x400.png",
                "popularStar": "5",
                "endTime": 0,
                "startTime": 1477030924,
                "title": "毛衣+荷叶边衬衫套装",
                "tag2": "",
                "tag3": "",
                "description": "爱它松软的舒适，爱它一针一线编织间穿插的回忆，爱它触感绵绵中包裹的温暖。秋雨的凉意袭来，有什么比一件慵懒的大毛衣更让你觉得舒服安心呢？",
                "tag1": "套装"
            },
            {
                "tagLink1": "mls://search/result?keyword=喇叭袖",
                "tagLink2": "",
                "tagLink3": "",
                "acm": "3.mce.2_10_1b9jm.9439.0.zlmCBqhId66VT.m_262765",
                "link": "http://item.meilishuo.com/h5/detail/1gp7toc?mt=12.9439.r189891.11228&acm=3.mce.2_10_1b9jm.9439.0.zlmCBqhId66VT.m_262765",
                "image": "http://s7.mogucdn.com/p2/161013/1sd_173ddbfia577l6d3e5l6dd3gk95dd_400x400.png",
                "popularStar": "5",
                "endTime": 0,
                "startTime": 1477030925,
                "title": "喇叭袖毛衣",
                "tag2": "",
                "tag3": "",
                "description": "兔绒针织毛衣，宽松荷叶喇叭袖，突然优雅女人气质。",
                "tag1": "喇叭袖"
            },
            {
                "tagLink1": "mls://search/result?keyword=珍珠",
                "tagLink2": "",
                "tagLink3": "",
                "acm": "3.mce.2_10_1b9jo.9439.0.zlmCBqhId66VU.m_262766",
                "link": "http://item.meilishuo.com/h5/detail/1gnmubu?mt=12.9439.r189889.11228&acm=3.mce.2_10_1b9jo.9439.0.zlmCBqhId66VU.m_262766",
                "image": "http://s7.mogucdn.com/p2/161013/1sp_70bkdch3e86hcbe55k6413736li17_400x400.jpg",
                "popularStar": "3",
                "endTime": 0,
                "startTime": 1477030924,
                "title": "粗跟珍珠及踝靴",
                "tag2": "",
                "tag3": "",
                "description": "nonono~不要碰我的珠宝！！",
                "tag1": "珍珠"
            },
            {
                "tagLink1": "mls://search/result?keyword=针织外套",
                "tagLink2": "",
                "tagLink3": "",
                "acm": "3.mce.2_10_1b9jq.9439.0.zlmCBqhId66VV.m_262767",
                "link": "http://item.meilishuo.com/h5/detail/1gpbmz2?mt=12.9439.r189895.11228&acm=3.mce.2_10_1b9jq.9439.0.zlmCBqhId66VV.m_262767",
                "image": "http://s7.mogucdn.com/p2/161013/1sd_208428i3gbjl45da9e7c0jfi285f9_400x400.png",
                "popularStar": "5",
                "endTime": 0,
                "startTime": 1477030934,
                "title": "针织长款外套",
                "tag2": "",
                "tag3": "",
                "description": "随意温暖又好穿，撞色小细节自然不突兀，这个秋季，就选它了！",
                "tag1": "针织外套"
            },
            {
                "tagLink1": "mls://search/result?keyword=卫衣裙",
                "tagLink2": "",
                "tagLink3": "",
                "acm": "3.mce.2_10_1b9js.9439.0.zlmCBqhId66VW.m_262768",
                "link": "http://item.meilishuo.com/h5/detail/1gp1eg2?mt=12.9439.r189900.11228&acm=3.mce.2_10_1b9js.9439.0.zlmCBqhId66VW.m_262768",
                "image": "http://s6.mogucdn.com/p2/161013/1sd_67dgh678eg2864f760aa3ja31a4la_400x400.png",
                "popularStar": "5",
                "endTime": 0,
                "startTime": 1477030942,
                "title": "卫衣裙",
                "tag2": "",
                "tag3": "",
                "description": "小宽松的直筒版型，是卫衣裙必备的显瘦版型，配合印花几何英文插肩型设计。 印花部分用了与黑色契合度满分的红与白，潮范儿十足哦！",
                "tag1": "卫衣裙"
            },
            {
                "tagLink1": "mls://search/result?keyword=针织",
                "tagLink2": "",
                "tagLink3": "",
                "acm": "3.mce.2_10_1b9ju.9439.0.zlmCBqhId66VX.m_262769",
                "link": "http://item.meilishuo.com/h5/detail/1fp0fmu?mt=12.9439.r189896.11228&acm=3.mce.2_10_1b9ju.9439.0.zlmCBqhId66VX.m_262769",
                "image": "http://s8.mogucdn.com/p2/161013/1sd_03ea78cjcdddi91clkbj0b42510ac_400x400.png",
                "popularStar": "5",
                "endTime": 0,
                "startTime": 1477030934,
                "title": "韩范儿针织外套",
                "tag2": "",
                "tag3": "",
                "description": "韩范儿小粉针织外套，甜美到不行的小热款！",
                "tag1": "针织"
            },
            {
                "tagLink1": "mls://search/result?keyword=粗跟",
                "tagLink2": "",
                "tagLink3": "",
                "acm": "3.mce.2_10_1b9jw.9439.0.zlmCBqhId66VY.m_262770",
                "link": "http://item.meilishuo.com/h5/detail/1gnujac?mt=12.9439.r189892.11228&acm=3.mce.2_10_1b9jw.9439.0.zlmCBqhId66VY.m_262770",
                "image": "http://s8.mogucdn.com/p2/161013/1sp_406jhk54c19l9b618bf1bll83k95b_468x608.jpg",
                "popularStar": "5",
                "endTime": 0,
                "startTime": 1477030925,
                "title": "高跟白色短靴",
                "tag2": "",
                "tag3": "",
                "description": "小白鞋那么火，白色短靴试试看，纯洁的白莲花~",
                "tag1": "粗跟"
            },
            {
                "tagLink1": "mls://search/result?keyword=套装",
                "tagLink2": "",
                "tagLink3": "",
                "acm": "3.mce.2_10_1b9jy.9439.0.zlmCBqhId66VZ.m_262771",
                "link": "http://item.meilishuo.com/h5/detail/1gly1uy?mt=12.9439.r189903.11228&acm=3.mce.2_10_1b9jy.9439.0.zlmCBqhId66VZ.m_262771",
                "image": "http://s7.mogucdn.com/p2/161013/1sd_3e2l74a7ej3010770f0ghc338j3gc_400x400.png",
                "popularStar": "5",
                "endTime": 0,
                "startTime": 1477030955,
                "title": "卫衣裙套装",
                "tag2": "",
                "tag3": "",
                "description": "进军潮流前线，将时尚一网打尽！~ 夺目抢眼的黑白撞色设计，搭配街头味十足的字母印花， 张扬的街拍格调展露出不羁的青春气息~",
                "tag1": "套装"
            },
            {
                "tagLink1": "mls://search/result?keyword=打底衫",
                "tagLink2": "",
                "tagLink3": "",
                "acm": "3.mce.2_10_1b9k0.9439.0.zlmCAqhId66V0.m_262772",
                "link": "http://item.meilishuo.com/h5/detail/1gp9kye?mt=12.9439.r189902.11228&acm=3.mce.2_10_1b9k0.9439.0.zlmCAqhId66V0.m_262772",
                "image": "http://s7.mogucdn.com/p2/161013/1sd_2c05g3b5hfkifk4fa5dg5k6e25g1k_400x400.png",
                "popularStar": "5",
                "endTime": 0,
                "startTime": 1477030955,
                "title": "打底针织衫",
                "tag2": "",
                "tag3": "",
                "description": "简直要被帅倒了！黑色打底针织衫，细节设计耐人寻味，整体简洁易搭，非常好穿的小款哦！",
                "tag1": "打底衫"
            },
            {
                "tagLink1": "mls://search/result?keyword=方头",
                "tagLink2": "",
                "tagLink3": "",
                "acm": "3.mce.2_10_1b9k2.9439.0.zlmCAqhId66V1.m_262773",
                "link": "http://item.meilishuo.com/h5/detail/1gn0yt8?mt=12.9439.r189894.11228&acm=3.mce.2_10_1b9k2.9439.0.zlmCAqhId66V1.m_262773",
                "image": "http://s8.mogucdn.com/p2/161013/1sp_1i5icai5g5e7hl471kj8fbfg0b3d0_400x400.jpg",
                "popularStar": "5",
                "endTime": 0,
                "startTime": 1477030934,
                "title": "异形跟跟小方头短靴",
                "tag2": "",
                "tag3": "",
                "description": "小小的方头，可爱的毛毛，是小可爱？是小魔女吧！",
                "tag1": "方头"
            },
            {
                "tagLink1": "mls://search/result?keyword=细跟",
                "tagLink2": "",
                "tagLink3": "",
                "acm": "3.mce.2_10_1b9k4.9439.0.zlmCAqhId66V2.m_262774",
                "link": "http://item.meilishuo.com/h5/detail/1gmr360?mt=12.9439.r189898.11228&acm=3.mce.2_10_1b9k4.9439.0.zlmCAqhId66V2.m_262774",
                "image": "http://s8.mogucdn.com/p2/161013/1sp_7a4j3dl2618f17ka46533j62e0680_400x400.jpg",
                "popularStar": "5",
                "endTime": 0,
                "startTime": 1477030942,
                "title": "细跟尖头切尔西靴",
                "tag2": "",
                "tag3": "",
                "description": "切尔西靴去年大卖，今年流行依旧~",
                "tag1": "细跟"
            },
            {
                "tagLink1": "mls://search/result?keyword=设计师款",
                "tagLink2": "mls://search/result?keyword=两三事",
                "tagLink3": "",
                "acm": "3.mce.2_10_1b9k6.9439.0.zlmCAqhId66V3.m_262775",
                "link": "http://item.meilishuo.com/h5/detail/1gp9288?mt=12.9439.r189907.11228&acm=3.mce.2_10_1b9k6.9439.0.zlmCAqhId66V3.m_262775",
                "image": "http://s6.mogucdn.com/p2/161009/1sd_22akj6i9bdc24bejbhgdgb23abcc9_400x400.png",
                "popularStar": "5",
                "endTime": 0,
                "startTime": 1477030972,
                "title": "两件套长袖连衣裙",
                "tag2": "两三事",
                "tag3": "",
                "description": "不规则两件套，独特的设计师款，虎头绣花＋不规则下摆元素，个性十足，赚足回头率！",
                "tag1": "设计师款"
            },
            {
                "tagLink1": "mls://search/result?keyword=棒球外套",
                "tagLink2": "",
                "tagLink3": "",
                "acm": "3.mce.2_10_1b9k8.9439.0.zlmCAqhId66V4.m_262776",
                "link": "http://item.meilishuo.com/h5/detail/1gp5yv0?mt=12.9439.r189906.11228&acm=3.mce.2_10_1b9k8.9439.0.zlmCAqhId66V4.m_262776",
                "popularStar": "5",
                "image": "http://s10.mogucdn.com/p2/161010/1sd_50b9756e2f6j02gbbfalgca39gk5e_400x400.jpg",
                "endTime": 0,
                "startTime": 1477030972,
                "tag2": "",
                "title": "棒球外套",
                "tag3": "",
                "description": "韩版潮人棒球外套，本季各路博主强力推荐的热销单品，你值得拥有！",
                "tag1": "棒球外套"
            },
            {
                "tagLink1": "mls://search/result?keyword=校园风",
                "tagLink2": "",
                "tagLink3": "",
                "acm": "3.mce.2_10_1b9ka.9439.0.zlmCAqhId66V5.m_262777",
                "link": "http://item.meilishuo.com/h5/detail/1gkx4ku?mt=12.9439.r189901.11228&acm=3.mce.2_10_1b9ka.9439.0.zlmCAqhId66V5.m_262777",
                "image": "http://s8.mogucdn.com/p2/161013/n5_2cl14ifj45h3kf3a7a482ddha8kg2_458x458.jpg",
                "popularStar": "5",
                "endTime": 0,
                "startTime": 1477030955,
                "title": "两杠数字运动短袜",
                "tag2": "",
                "tag3": "",
                "description": "袜子上的小心机，给你满满校园风！",
                "tag1": "校园风"
            },
            {
                "tagLink1": "mls://search/result?keyword=机车",
                "tagLink2": "",
                "tagLink3": "",
                "acm": "3.mce.2_10_1b9kc.9439.0.zlmCAqhId66V6.m_262778",
                "link": "http://item.meilishuo.com/h5/detail/1gmzp4q?mt=12.9439.r189893.11228&acm=3.mce.2_10_1b9kc.9439.0.zlmCAqhId66V6.m_262778",
                "image": "http://s7.mogucdn.com/p2/161013/1sp_4l7di91a005e7l74a15h23j96bce7_400x400.jpg",
                "popularStar": "5",
                "endTime": 0,
                "startTime": 1477030934,
                "title": "粗跟厚底机车靴",
                "tag2": "",
                "tag3": "",
                "description": "朋克风席卷街头，配上皮衣帅呆了！",
                "tag1": "机车"
            },
            {
                "tagLink1": "",
                "tagLink2": "",
                "tagLink3": "",
                "acm": "3.mce.2_10_1b9ke.9439.0.zlmCAqhId66V7.m_262779",
                "link": "http://item.meilishuo.com/h5/detail/1glyf50?mt=12.9439.r189908.11228&acm=3.mce.2_10_1b9ke.9439.0.zlmCAqhId66V7.m_262779",
                "popularStar": "4",
                "image": "http://s8.mogucdn.com/p2/161011/1sx_143f74e7k5eflcificb25j84j91kg_400x400.jpg",
                "endTime": 0,
                "startTime": 1477030972,
                "tag2": "",
                "title": "时尚小猫包",
                "tag3": "",
                "description": "总得有个小猫包吧！",
                "tag1": ""
            },
            {
                "tagLink1": "mls://search/result?keyword=卫衣",
                "tagLink2": "",
                "tagLink3": "",
                "acm": "3.mce.2_10_1b9kg.9439.0.zlmCAqhId66V8.m_262780",
                "link": "http://item.meilishuo.com/h5/detail/1gmumri?mt=12.9439.r189911.11228&acm=3.mce.2_10_1b9kg.9439.0.zlmCAqhId66V8.m_262780",
                "image": "http://s10.mogucdn.com/p2/161009/1sd_4h8i888h55heb0dji3i34j0blig5l_400x400.png",
                "popularStar": "5",
                "endTime": 0,
                "startTime": 1477030972,
                "title": "糖力家拼色卫衣",
                "tag2": "",
                "tag3": "",
                "description": "糖力2016冬装新款——女装圆领长袖拼色卫衣，显瘦修身，出彩搭配！",
                "tag1": "卫衣"
            },
            {
                "tagLink1": "mls://search/result?keyword=套装",
                "tagLink2": "",
                "tagLink3": "",
                "acm": "3.mce.2_10_1b9ki.9439.0.zlmCAqhId66V9.m_262781",
                "link": "http://item.meilishuo.com/h5/detail/1glcqi2?mt=12.9439.r189912.11228&acm=3.mce.2_10_1b9ki.9439.0.zlmCAqhId66V9.m_262781",
                "popularStar": "5",
                "image": "http://s6.mogucdn.com/p2/161010/1sd_7eha3b74a8ai0blgdkj3l9agh1gee_400x400.jpg",
                "endTime": 0,
                "startTime": 1477030972,
                "tag2": "",
                "title": "针织背心+蕾丝连衣裙套装",
                "tag3": "",
                "description": "无论是针织背心或是蕾丝裙都是可以分开自行搭配的哦，均是百搭单品，可以分开购买~~~",
                "tag1": "套装"
            },
            {
                "tagLink1": "mls://search/result?keyword=口红",
                "tagLink2": "mls://search/result?keyword=润唇膏",
                "tagLink3": "",
                "acm": "3.mce.2_10_1b9kk.9439.0.zlmCAqhId66Va.m_262782",
                "link": "http://item.meilishuo.com/h5/detail/1fu75zm?mt=12.9439.r189910.11228&acm=3.mce.2_10_1b9kk.9439.0.zlmCAqhId66Va.m_262782",
                "popularStar": "4",
                "image": "http://s7.mogucdn.com/p2/161011/1ub_8e166hcdfbbid16hkdgd9kheddl6i_400x400.jpg",
                "endTime": 0,
                "startTime": 1477030972,
                "tag2": "润唇膏",
                "title": "bbia丝绒哑光唇膏",
                "tag3": "",
                "description": "pony同款唇膏，BBIA热卖的当家，哑光雾面，金秋最流行！",
                "tag1": "口红"
            },
            {
                "tagLink1": "mls://search/result?keyword=复古",
                "tagLink2": "",
                "tagLink3": "",
                "acm": "3.mce.2_10_1b9km.9439.0.zlmCAqhId66Vb.m_262783",
                "link": "http://item.meilishuo.com/h5/detail/1gnped0?mt=12.9439.r189897.11228&acm=3.mce.2_10_1b9km.9439.0.zlmCAqhId66Vb.m_262783",
                "image": "http://s7.mogucdn.com/p2/161013/1sp_7k51j24bf1353928kfl7355ib4gj2_400x400.jpg",
                "popularStar": "5",
                "endTime": 0,
                "startTime": 1477030941,
                "title": "复古坡跟厚底及踝靴",
                "tag2": "",
                "tag3": "",
                "description": "复古坡跟及踝靴，经典雕花适合文艺的你！",
                "tag1": "复古"
            },
            {
                "tagLink1": "mls://search/result?keyword=流苏",
                "tagLink2": "",
                "tagLink3": "",
                "acm": "3.mce.2_10_1b9ko.9439.0.zlmCAqhId66Vc.m_262784",
                "link": "http://item.meilishuo.com/h5/detail/1gmr3qs?mt=12.9439.r189904.11228&acm=3.mce.2_10_1b9ko.9439.0.zlmCAqhId66Vc.m_262784",
                "image": "http://s7.mogucdn.com/p2/161013/1sp_3e122kf73j7hj5di5db474g13g16j_400x400.jpg",
                "popularStar": "5",
                "endTime": 0,
                "startTime": 1477030955,
                "title": "流苏系带及踝靴",
                "tag2": "",
                "tag3": "",
                "description": "饱满如同羽翼的流苏，不知道高品位的你喜欢嘛？",
                "tag1": "流苏"
            },
            {
                "tagLink1": "mls://search/result?keyword=尖头",
                "tagLink2": "",
                "tagLink3": "",
                "acm": "3.mce.2_10_1b9kq.9439.0.zlmCAqhId66Vd.m_262785",
                "link": "http://item.meilishuo.com/h5/detail/1gm4blc?mt=12.9439.r189905.11228&acm=3.mce.2_10_1b9kq.9439.0.zlmCAqhId66Vd.m_262785",
                "image": "http://s6.mogucdn.com/p2/161013/1sp_5194gf2gffd5603ed9a526iheb2b0_400x400.jpg",
                "popularStar": "5",
                "endTime": 0,
                "startTime": 1477030955,
                "title": "细跟尖头高跟踝靴",
                "tag2": "",
                "tag3": "",
                "description": "超高跟+尖头+金属小装饰，显高显瘦凸显小心机。",
                "tag1": "尖头"
            },
            {
                "tagLink1": "mls://search/result?keyword=铆钉",
                "tagLink2": "",
                "tagLink3": "",
                "acm": "3.mce.2_10_1b9ks.9439.0.zlmCAqhId66Ve.m_262786",
                "link": "http://item.meilishuo.com/h5/detail/1gnx41k?mt=12.9439.r189909.11228&acm=3.mce.2_10_1b9ks.9439.0.zlmCAqhId66Ve.m_262786",
                "image": "http://s10.mogucdn.com/p2/161010/1sp_5526hidaldlalh8l1b84c8dfkflb3_400x400.jpg",
                "popularStar": "5",
                "endTime": 0,
                "startTime": 1477030972,
                "title": "牛皮铆钉切尔西靴",
                "tag2": "",
                "tag3": "",
                "description": "铆钉切尔西靴，有比这个更酷的吗？",
                "tag1": "铆钉"
            },
            {
                "tagLink1": "mls://search/result?keyword=混色",
                "tagLink2": "",
                "tagLink3": "",
                "acm": "3.mce.2_10_1b9ku.9439.0.zlmCAqhId66Vf.m_262787",
                "link": "http://item.meilishuo.com/h5/detail/1go1chm?mt=12.9439.r189919.11228&acm=3.mce.2_10_1b9ku.9439.0.zlmCAqhId66Vf.m_262787",
                "popularStar": "5",
                "image": "http://s8.mogucdn.com/p2/161011/n5_0c5ik9eil4he6i7chebl5ak396dd3_640x640.jpg",
                "endTime": 0,
                "startTime": 1477030973,
                "tag2": "",
                "title": "秋冬混色加厚围巾",
                "tag3": "",
                "description": "简约又百搭，暖过男朋友！",
                "tag1": "混色"
            },
            {
                "tagLink1": "mls://search/result?keyword=牛仔外套",
                "tagLink2": "mls://search/result?keyword=实穿百搭",
                "tagLink3": "",
                "acm": "3.mce.2_10_1b9kw.9439.0.zlmCAqhId66Vg.m_262788",
                "link": "http://item.meilishuo.com/h5/detail/1glyz6e?mt=12.9439.r189923.11228&acm=3.mce.2_10_1b9kw.9439.0.zlmCAqhId66Vg.m_262788",
                "popularStar": "5",
                "image": "http://s10.mogucdn.com/p2/160905/1sd_15c03f0j9kih68h1flha96g66c45e_400x400.jpg",
                "endTime": 0,
                "startTime": 1477030973,
                "tag2": "实穿百搭",
                "title": "百搭牛仔外套",
                "tag3": "",
                "description": "牛仔外套一直以来都是时尚潮人的宠儿！尤其是今年，经典牛仔越演越烈，火热依旧延续。这款BF风格的牛仔外套，自带时尚气息的廓形，随手一穿，时尚度甩出一条街啊！",
                "tag1": "牛仔外套"
            },
            {
                "tagLink1": "mls://search/result?keyword=面膜",
                "tagLink2": "mls://search/result?keyword=韩国热卖",
                "tagLink3": "",
                "acm": "3.mce.2_10_1b9ky.9439.0.zlmCAqhId66Vh.m_262789",
                "link": "http://item.meilishuo.com/h5/detail/1gp64w4?mt=12.9439.r189913.11228&acm=3.mce.2_10_1b9ky.9439.0.zlmCAqhId66Vh.m_262789",
                "popularStar": "4",
                "image": "http://s7.mogucdn.com/p2/161011/1ub_36fg1keh38kfklkl2722k02743l44_400x400.jpg",
                "endTime": 0,
                "startTime": 1477030972,
                "tag2": "韩国热卖",
                "title": "JAYJUN水光面膜",
                "tag3": "",
                "description": "火爆韩国的水光面膜，敷出不需要打针的水光嫩滑肌肤",
                "tag1": "面膜"
            },
            {
                "tagLink1": "mls://search/result?keyword=系带",
                "tagLink2": "",
                "tagLink3": "",
                "acm": "3.mce.2_10_1b9l0.9439.0.zlmCAqhId66Vi.m_262790",
                "link": "http://item.meilishuo.com/h5/detail/1gox788?mt=12.9439.r189914.11228&acm=3.mce.2_10_1b9l0.9439.0.zlmCAqhId66Vi.m_262790",
                "image": "http://s7.mogucdn.com/p2/161010/1sp_88c4gk1l591e1k7dd2a551f4567cd_400x400.jpg",
                "popularStar": "5",
                "endTime": 0,
                "startTime": 1477030972,
                "title": "粗跟系带高筒靴",
                "tag2": "",
                "tag3": "",
                "description": "系带长靴，凸显纤细腿型",
                "tag1": "系带"
            },
            {
                "tagLink1": "mls://search/result?keyword=堆堆袜",
                "tagLink2": "",
                "tagLink3": "",
                "acm": "3.mce.2_10_1b9l2.9439.0.zlmCAqhId66Vj.m_262791",
                "link": "http://item.meilishuo.com/h5/detail/1gmjx76?mt=12.9439.r189915.11228&acm=3.mce.2_10_1b9l2.9439.0.zlmCAqhId66Vj.m_262791",
                "image": "http://s7.mogucdn.com/p2/161011/n5_5ec733cb1ce3kllhc16bgkk2iglhi_640x640.jpg",
                "popularStar": "5",
                "endTime": 0,
                "startTime": 1477030972,
                "title": "秋冬兔羊毛针织袜",
                "tag2": "",
                "tag3": "",
                "description": "从脚底暖到心里！",
                "tag1": "堆堆袜"
            },
            {
                "tagLink1": "",
                "tagLink2": "",
                "tagLink3": "",
                "acm": "3.mce.2_10_1b9l4.9439.0.zlmCAqhId66Vk.m_262792",
                "link": "http://item.meilishuo.com/h5/detail/1gktoq6?mt=12.9439.r189916.11228&acm=3.mce.2_10_1b9l4.9439.0.zlmCAqhId66Vk.m_262792",
                "image": "http://s6.mogucdn.com/p2/161011/1sx_1d6h9kj7fa2g1617dc75cdlllf6l1_400x400.jpg",
                "popularStar": "4",
                "endTime": 0,
                "startTime": 1477030972,
                "title": "帅气双肩包",
                "tag2": "",
                "tag3": "",
                "description": "两根带子简直是减龄的秘籍，不管是背带裤还是双肩包！",
                "tag1": ""
            }
        ],
        "nextPage": 2
    },
    "returnCode": "SUCCESS",
    "success": true
}